{
	"asset":{
		"version":"0.0",
		"tilesetVersion":"1.2.3"
	},

	"geometricError":1,

	"root":{
		"boundingVolume":{
			"sphere":[6358636.3844169835,-499269.88962804078,254.7128273223621,14.437538146972656]
		},
		"geometricError":1,
		"content":{
			"url":"Tile_+000_+008_L21_0000200.b3dm"
		},
		"children":[
			{
				"boundingVolume":{
					"sphere":[6358636.3679208588,-499269.8883326932,254.68167284631053,14.375984191894531]
				},
				"geometricError":0.5,
				"content":{
					"url":"Tile_+000_+008_L22_00002000.b3dm"
				}
			}
		]
	}
}