{
	"asset":{
		"version":"0.0",
		"tilesetVersion":"1.2.3"
	},

	"geometricError":1,

	"root":{
		"boundingVolume":{
			"sphere":[6358701.6662969477,-498892.04528575868,-497.53691790999369,0.434229969978333]
		},
		"geometricError":1,
		"content":{
			"url":"Tile_+004_+000_L21_0003000.b3dm"
		},
		"children":[
			{
				"boundingVolume":{
					"sphere":[6358701.6903394759,-498892.05859324767,-497.53691980387771,0.409220218658447]
				},
				"geometricError":0.5,
				"content":{
					"url":"Tile_+004_+000_L22_00030000.b3dm"
				}
			}
		]
	}
}