{
	"asset":{
		"version":"0.0",
		"tilesetVersion":"1.2.3"
	},

	"geometricError":2,

	"root":{
		"boundingVolume":{
			"sphere":[6358705.7118556285,-499175.83701350942,-70.485038513895844,25.896123886108398]
		},
		"geometricError":2,
		"content":{
			"url":"Tile_+001_+004_L20_000310t3.b3dm"
		},
		"children":[
			{
				"boundingVolume":{
					"sphere":[6358694.1857483052,-499180.93516283372,-71.225169541586979,16.265753269195557]
				},
				"geometricError":1,
				"content":{
					"url":"Tile_+001_+004_L21_0003100t2.json"
				}
			},
			{
				"boundingVolume":{
					"sphere":[6358695.0697515439,-499168.89468681527,-70.405543730285046,16.630894184112549]
				},
				"geometricError":1,
				"content":{
					"url":"Tile_+001_+004_L21_0003110t2.json"
				}
			},
			{
				"boundingVolume":{
					"sphere":[6358715.1898244442,-499182.67216455919,-71.152487621465482,15.058293342590332]
				},
				"geometricError":1,
				"content":{
					"url":"Tile_+001_+004_L21_0003120t3.json"
				}
			},
			{
				"boundingVolume":{
					"sphere":[6358716.3597391034,-499170.63608768699,-70.317429669505344,15.530305862426758]
				},
				"geometricError":1,
				"content":{
					"url":"Tile_+001_+004_L21_0003130t3.json"
				}
			}
		]
	}
}