{
	"asset":{
		"version":"0.0",
		"tilesetVersion":"1.2.3"
	},

	"geometricError":2,

	"root":{
		"boundingVolume":{
			"sphere":[6358720.801311315,-498942.99523518054,-391.19030596344226,19.111763000488281]
		},
		"geometricError":2,
		"content":{
			"url":"Tile_+004_+001_L20_000400t3.b3dm"
		},
		"children":[
			{
				"boundingVolume":{
					"sphere":[6358714.4967255862,-498950.65077504137,-395.39451502001009,8.702043533325195]
				},
				"geometricError":1,
				"content":{
					"url":"Tile_+004_+001_L21_0004000.json"
				}
			},
			{
				"boundingVolume":{
					"sphere":[6358715.9878059505,-498931.65498301457,-386.31400989071085,7.031281471252441]
				},
				"geometricError":1,
				"content":{
					"url":"Tile_+004_+001_L21_0004010.json"
				}
			},
			{
				"boundingVolume":{
					"sphere":[6358725.8315712642,-498951.57341471885,-395.35865485054347,8.688194274902344]
				},
				"geometricError":1,
				"content":{
					"url":"Tile_+004_+001_L21_0004020.json"
				}
			},
			{
				"boundingVolume":{
					"sphere":[6358727.3217369132,-498932.5893420442,-386.19988262307527,7.070174694061279]
				},
				"geometricError":1,
				"content":{
					"url":"Tile_+004_+001_L21_0004030.json"
				}
			}
		]
	}
}