{
	"asset":{
		"version":"0.0",
		"tilesetVersion":"1.2.3"
	},

	"geometricError":2,

	"root":{
		"boundingVolume":{
			"sphere":[6358702.0520278141,-498928.60429858643,-379.47007880025598,8.793267250061035]
		},
		"geometricError":2,
		"content":{
			"url":"Tile_+004_+001_L20_000340.b3dm"
		},
		"children":[
			{
				"boundingVolume":{
					"sphere":[6358701.9978242368,-498928.66254509718,-379.41981516253605,8.705634117126465]
				},
				"geometricError":1,
				"content":{
					"url":"Tile_+004_+001_L21_0003400.json"
				}
			}
		]
	}
}