{
	"asset":{
		"version":"0.0",
		"tilesetVersion":"1.2.3"
	},

	"geometricError":1,

	"root":{
		"boundingVolume":{
			"sphere":[6358659.0341664674,-499037.04430612182,-18.443122151785822,19.485340118408203]
		},
		"geometricError":1,
		"content":{
			"url":"Tile_+003_+005_L21_0002100.b3dm"
		},
		"children":[
			{
				"boundingVolume":{
					"sphere":[6358659.033463126,-499037.07550063968,-18.443122149731749,19.423608779907227]
				},
				"geometricError":0.5,
				"content":{
					"url":"Tile_+003_+005_L22_00021000.b3dm"
				}
			}
		]
	}
}