{
	"asset":{
		"version":"0.0",
		"tilesetVersion":"1.2.3"
	},

	"geometricError":500,

	"root":{
		"boundingVolume":{
			"sphere":[6358666.2052144567,-498899.88965731021,289.97979321084142,69.423957824707031]
		},
		"geometricError":500,
		"content":{
			"url":"Tile_+004_+008.b3dm"
		},
		"children":[
			{
				"boundingVolume":{
					"sphere":[6358666.2052144567,-498899.88965731021,289.97979321084142,69.423957824707031]
				},
				"geometricError":64,
				"content":{
					"url":"Tile_+004_+008_L15_0.json"
				}
			}
		]
	}
}