{
	"asset":{
		"version":"0.0",
		"tilesetVersion":"1.2.3"
	},

	"geometricError":1,

	"root":{
		"boundingVolume":{
			"sphere":[6358717.823874264,-499042.83860772848,-340.33884050425058,10.073955535888672]
		},
		"geometricError":1,
		"content":{
			"url":"Tile_+003_+002_L21_0004010.b3dm"
		},
		"children":[
			{
				"boundingVolume":{
					"sphere":[6358717.8214350464,-499042.86966643331,-340.36999458542101,10.001711845397949]
				},
				"geometricError":0.5,
				"content":{
					"url":"Tile_+003_+002_L22_00040100.b3dm"
				}
			}
		]
	}
}