{
	"asset":{
		"version":"0.0",
		"tilesetVersion":"1.2.3"
	},

	"geometricError":1,

	"root":{
		"boundingVolume":{
			"sphere":[6358681.3148219567,-499107.16671336844,101.42299467056907,14.636011123657227]
		},
		"geometricError":1,
		"content":{
			"url":"Tile_+002_+006_L21_0001320.b3dm"
		},
		"children":[
			{
				"boundingVolume":{
					"sphere":[6358681.3172593089,-499107.13565486809,101.45414874218042,14.560312271118164]
				},
				"geometricError":0.5,
				"content":{
					"url":"Tile_+002_+006_L22_00013200.b3dm"
				}
			}
		]
	}
}